[
      {
        "name": "Samaypur Badli",
        "lines": ["Yellow"]
      },
      {
        "name": "Rohini Sector 18, 19",
        "lines": ["Yellow"]
      },
      {
        "name": "Haiderpur Badli Mor",
        "lines": ["Yellow"]
      },
      {
        "name": "Jahangirpuri",
        "lines": ["Yellow"]
      },
      {
        "name": "Adarsh Nagar",
        "lines": ["Yellow"]
      },
      {
        "name": "Azadpur",
        "lines": ["Yellow","Pink"]
      },
      {
        "name": "Model Town",
        "lines": ["Yellow"]
      },
      {
        "name": "GTB Nagar",
        "lines": ["Yellow"]
      },
      {
        "name": "Vishwa Vidyalaya",
        "lines": ["Yellow"]
      },
      {
        "name": "Vidhan Sabha",
        "lines": ["Yellow"]
      },
      {
        "name": "Civil Lines",
        "lines": ["Yellow"]
      },
      {
        "name": "Kashmere Gate",
        "lines": ["Yellow", "Red", "Violet"]
      },
      {
        "name": "Chandni Chowk",
        "lines": ["Yellow"]
      },
      {
        "name": "Chawri Bazar",
        "lines": ["Yellow"]
      },
      {
        "name": "New Delhi",
        "lines": ["Yellow", "Orange"]
      },
      {
        "name": "Rajiv Chowk",
        "lines": ["Yellow", "Blue"]
      },
      {
        "name": "Patel Chowk",
        "lines": ["Yellow"]
      },
      {
        "name": "Central Secretariat",
        "lines": ["Yellow", "Violet"]
      },
      {
        "name": "Udyog Bhawan",
        "lines": ["Yellow"]
      },
      {
        "name": "Lok Kalyan Marg",
        "lines": ["Yellow"]
      },
      {
        "name": "Jor Bagh",
        "lines": ["Yellow"]
      },
      {
        "name": "Dilli Haat - INA",
        "lines": ["Yellow", "Pink"]
      },
      {
        "name": "AIIMS",
        "lines": ["Yellow", "Magenta"]
      },
      {
        "name": "Green Park",
        "lines": ["Yellow"]
      },
      {
        "name": "Hauz Khas",
        "lines": ["Yellow", "Magenta"]
      },
      {
        "name": "Malviya Nagar",
        "lines": ["Yellow"]
      },
      {
        "name": "Saket",
        "lines": ["Yellow"]
      },
      {
        "name": "Qutab Minar",
        "lines": ["Yellow"]
      },
      {
        "name": "Chhatarpur",
        "lines": ["Yellow"]
      },
      {
        "name": "Sultanpur",
        "lines": ["Yellow"]
      },
      {
        "name": "Ghitorni",
        "lines": ["Yellow"]
      },
      {
        "name": "Arjan Garh",
        "lines": ["Yellow"]
      },
      {
        "name": "Guru Dronacharya",
        "lines": ["Yellow"]
      },
      {
        "name": "Sikanderpur",
        "lines": ["Yellow"]
      },
      {
        "name": "MG Road",
        "lines": ["Yellow"]
      },
      {
        "name": "IFFCO Chowk",
        "lines": ["Yellow"]
      },
      {
        "name": "Millennium City Centre Gurugram",
        "lines": ["Yellow"]
      }
    ]
  
  